{
    "Version": "2012-10-17",
    "Statement": [
        {
            "Effect": "Allow",
            "Principal": {
                "Federated": "arn:aws:iam::331924599099:oidc-provider/oidc.eks.us-east-1.amazonaws.com/id/{{EKS_CLUSTER_ID}}"
            },
            "Action": "sts:AssumeRoleWithWebIdentity",
            "Condition": {
                "StringEquals": {
                    "oidc.eks.us-east-1.amazonaws.com/id/{{EKS_CLUSTER_ID}}:sub": "system:serviceaccount:pepr-system:pepr-b95dbd80-e078-5eb9-aaf3-bcb9567417d0"
                }
            }
        }
    ]
}
